anserializer/__init__.py
anserializer/serializer.py
anserializer/serializers/__init__.py
anserializer/serializers/baseserializer.py
anserializer/serializers/datetimeserializer.py
anserializer/serializers/enumserializer.py
anserializer/serializers/objectserializer.py
anserializer-1.2.2.dist-info/LICENSE
anserializer-1.2.2.dist-info/METADATA
anserializer-1.2.2.dist-info/WHEEL
anserializer-1.2.2.dist-info/top_level.txt
anserializer-1.2.2.dist-info/RECORD
