Metadata-Version: 2.1
Name: anserializer
Version: 1.2.2
Summary: A serializer/deserializer mechanism for simple and complex data structures
Home-page: https://github.com/anttin/anserializer
Author: anttin
Author-email: muut.py@antion.fi
License: UNKNOWN
Platform: UNKNOWN
Classifier: Programming Language :: Python :: 3
Classifier: License :: OSI Approved :: MIT License
Classifier: Operating System :: OS Independent
License-File: LICENSE
